{
	"description": "项目配置文件",
	"packOptions": {
		"ignore": []
	},
	"setting": {
		"urlCheck": true,
		"es6": true,
		"postcss": true,
		"minified": true,
		"newFeature": true,
		"coverView": true,
		"nodeModules": true,
		"autoAudits": false,
		"showShadowRootInWxmlPanel": true,
		"scopeDataCheck": false,
		"checkInvalidKey": true,
		"checkSiteMap": true,
		"uploadWithSourceMap": true,
		"babelSetting": {
			"ignore": [],
			"disablePlugins": [],
			"outputPath": ""
		}
	},
	"compileType": "miniprogram",
	"libVersion": "2.11.0",
	"appid": "wxf859d23ddc4c22ea",
	"projectname": "miniprogram-1",
	"debugOptions": {
		"hidedInDevtools": []
	},
	"isGameTourist": false,
	"simulatorType": "wechat",
	"simulatorPluginLibVersion": {},
	"condition": {
		"search": {
			"current": -1,
			"list": []
		},
		"conversation": {
			"current": -1,
			"list": []
		},
		"plugin": {
			"current": -1,
			"list": []
		},
		"game": {
			"currentL": -1,
			"list": []
		},
		"gamePlugin": {
			"current": -1,
			"list": []
		},
		"miniprogram": {
			"current": -1,
			"list": [
				{
					"id": 0,
					"name": "pages/login/login",
					"pathName": "pages/login/login",
					"query": "",
					"scene": null
				},
				{
					"id": -1,
					"name": "pages/my/my",
					"pathName": "pages/my/my",
					"query": "",
					"scene": null
				},
				{
					"id": -1,
					"name": "pages/login/login",
					"pathName": "pages/login/login",
					"query": "",
					"scene": null
				},
				{
					"id": -1,
					"name": "pages/index/index",
					"pathName": "pages/index/index",
					"query": "",
					"scene": null
				},
				{
					"id": -1,
					"name": "pages/search/search",
					"pathName": "pages/search/search",
					"query": "",
					"scene": null
				},
				{
					"id": -1,
					"name": "pages/train_list/train_list",
					"pathName": "pages/train_list/train_list",
					"query": "",
					"scene": null
				},
				{
					"id": -1,
					"name": "pages/register/register",
					"pathName": "pages/register/register",
					"query": "",
					"scene": null
				},
				{
					"id": -1,
					"name": "pages/message/message",
					"pathName": "pages/message/message",
					"query": "",
					"scene": null
				},
				{
					"id": -1,
					"name": "pages/shopcar/shopcar",
					"pathName": "pages/shopcar/shopcar",
					"query": "",
					"scene": null
				},
				{
					"id": -1,
					"name": "pages/scan_code/scan_code",
					"pathName": "pages/scan_code/scan_code",
					"query": "",
					"scene": null
				},
				{
					"id": -1,
					"name": "pages/scan_code/scan_code",
					"pathName": "pages/scan_code/scan_code",
					"query": "",
					"scene": null
				},
				{
					"id": -1,
					"name": "pages/unpaid/unpaid",
					"pathName": "pages/unpaid/unpaid",
					"query": "",
					"scene": null
				},
				{
					"id": -1,
					"name": "pages/unpaid/unpaid",
					"pathName": "pages/unpaid/unpaid",
					"query": "",
					"scene": null
				},
				{
					"id": -1,
					"name": "pages/kefu/kefu",
					"pathName": "pages/kefu/kefu",
					"query": "",
					"scene": null
				},
				{
					"id": -1,
					"name": "pages/kefu/kefu",
					"pathName": "pages/kefu/kefu",
					"query": "",
					"scene": null
				},
				{
					"id": -1,
					"name": "pages/test/test",
					"pathName": "pages/test/test",
					"query": "",
					"scene": null
				},
				{
					"id": -1,
					"name": "pages/paid/paid",
					"pathName": "pages/paid/paid",
					"scene": null
				}
			]
		}
	}
}